Workbook
Name HWSheet: 1
Name \a: #N/A
Name \b: #N/A
Name _: "="
Name ____________a11: {"'장비'!$A$3:$M$12"}
Name ____________H3: {"'장비'!$A$3:$M$12"}
Name ______a11: {"'장비'!$A$3:$M$12"}
Name ______H3: {"'장비'!$A$3:$M$12"}
Name ____a11: {"'장비'!$A$3:$M$12"}
Name ____H3: {"'장비'!$A$3:$M$12"}
Name __a11: {"'장비'!$A$3:$M$12"}
Name __DemandLoad: TRUE
Name __H3: {"'장비'!$A$3:$M$12"}
Name __IntlFixup: TRUE
Name __tt1: "tt1"
Name _10A1_: {"Book1","civilbm.xls"}
Name _14A1_: {"Book1","civilbm.xls"}
Name _A1: {"Book1","civilbm.xls"}
Name _Regression_Int: 1
Name _tt1: "tt1"
Name √: "SQRT"
Name AAA: {"'장비'!$A$3:$M$12"}
Name aaafff: {"'장비'!$A$3:$M$12"}
Name ADITION: {"'장비'!$A$3:$M$12"}
Name ads: BlankMacro1
Name afsdf: {"Book1","civilbm.xls"}
Name agfg: {"'장비'!$A$3:$M$12"}
Name ANC: "Edit Box 57"
Name ASDD: {"Book1","attach.xls"}
Name basin: {"'장비'!$A$3:$M$12"}
Name Button_3: "vlvlist_vlvlist_List"
Name cbcv: {"Book1","civilbm.xls"}
Name civil2: {"'장비'!$A$3:$M$12"}
Name coping: BLCH
Name dddf: {"'장비'!$A$3:$M$12"}
Name Deck3: "Group 246"
Name dfdf: {"'장비'!$A$3:$M$12"}
Name dfdsfsdaf: BlankMacro1
Name dfgdf: {"Book1","civilbm.xls"}
Name DFGSDFGSDGSD: {"'장비'!$A$3:$M$12"}
Name DIAMOND: {"'장비'!$A$3:$M$12"}
Name ds: {"Book1","civilbm.xls"}
Name DSFS: {"Book1","attach.xls"}
Name ert: {"'장비'!$A$3:$M$12"}
Name erty: {"'장비'!$A$3:$M$12"}
Name ewrweq: {"'장비'!$A$3:$M$12"}
Name fda: BlankMacro1
Name fffffffg: {"'장비'!$A$3:$M$12"}
Name ffgfg: {"'장비'!$A$3:$M$12"}
Name fgfj: {"Book1","civilbm.xls"}
Name gd: BlankMacro1
Name gdd: {"Book1","civilbm.xls"}
Name ggg: BlankMacro1
Name gggg: {"'장비'!$A$3:$M$12"}
Name ggggg: {"'장비'!$A$3:$M$12"}
Name HTML: {"'장비'!$A$3:$M$12"}
Name HTML1: {"'장비'!$A$3:$M$12"}
Name kjkgh: {"'장비'!$A$3:$M$12"}
Name LCD: {"Book1","civilbm.xls"}
Name level: {"'장비'!$A$3:$M$12"}

Sheet 分项汇总表
B1: 拉迪亚码头投标报价表-二航院
B2: 序号 | C2: 名称 | D2: 二航院方案（PHC桩）
D3: 金额（美元）
B4: B | C4: 准备工作 | D4: ='清单 '!H96 -> 88722
B5: C | C5: 疏浚工程
B6: D | C6: 地基处理 | D6: ='清单 '!H177 -> 16476810
B7: E | C7: 码头 | D7: ='清单 '!H416-D8 -> 50033437
C8: 护岸 | D8: =SUM('清单 '!H353:H364) -> 23514886
B9: F | C9: 路面工程 | D9: ='清单 '!H1127 -> 29471443
B10: G | C10: 电气 | D10: ='清单 '!H1405 -> 14606322
B11: H | C11: 房建 | D11: ='清单 '!H1995 -> 1119479
B12: I | C12: Gate Complex | D12: ='清单 '!H2148 -> 1977668
C13: 直接费小计 | D13: =SUM(D4:D12) -> 137288767
C14: 关税 | D14: 11685730
C15: 项目总计 | D15: =SUM(D13:D14) -> 1.489745e+08

Sheet 清单 
B1: THE BILL OF QUANTITIES（拉迪亚码头-港湾-二航院）
B2: Item No. | C2: Description2 | D2: 清单说明 | E2: Unit2 | F2: Quantity
G3: 综合单价（美元） | H3: 合计（美元）
B5: CLASS A | C5: PRELIMANARIES | D5: PRELIMANARIES
B6: A.1 | C6: Fixed (non-time related) Items | D6: 固定（非计时）项目
B7: A.1.1 | C7: Site Establishment | D7: 场地建设 | E7: LS | F7: 1
B8: A.1.2 | C8: Site Disestablishment | D8: 场地拆除 | E8: LS | F8: 1
B9: A.1.3 | C9: Temporary Access Routes | D9: 临时道路 | E9: LS | F9: 1
B10: A.1.4 | C10: Safety & Emergency Response | D10: 安全与应急响应 | E10: LS | F10: 1
B11: A.1.5 | C11: Risk Assessment /Method Statements / HSSE Plan | D11: 风险评估/方法说明/健康安全环境计划 | E11: LS | F11: 1
B12: A.1.6 | C12: Quality Management/Assurance Plan | D12: 质量管理／保证计划 | E12: LS | F12: 1
B13: A.1.7 | C13: Contractor’s Environmental and Social Management Plan | D13: 承包商环境与社会管理计划 | E13: LS | F13: 1
B14: A.1.8 | C14: Engineers' Site Facilities | D14: 工程师现场设施设备 | E14: LS | F14: 1
B15: A.1.9 | C15: Project Security (establishment) | D15: 项目保安（设立） | E15: LS | F15: 1
B16: A.1.10 | C16: Mobilisation of Contractor's Plant and Equipment | D16: 承包商设备与机械进场
C17: Contractor to itemise major plant | D17: 承包商列明主要设备 | E17: LS | F17: 1
B18: A.1.10.1 | C18: Piling rigs | D18: 桩机 | E18: LS | F18: 1
B19: A.1.10.2 | C19: Cranes | D19: 起重机 | E19: LS | F19: 1
B20: A.1.10.3 | C20: Paving machines | D20: 铺路机械 | E20: LS | F20: 1
B21: A.1.10.X | C21: Other equipment - Contractor to specify | D21: 其他设备——由承包商指定 | E21: LS | F21: 1
B22: A.1.11 | C22: De-mobilisation of Contractor's Plant & Equipment | D22: 承包商设备与机械退场 | E22: LS | F22: 1
B23: A.1.12 | C23: Insurances | D23: 保险 | E23: LS | F23: 1
B24: A.1.13 | C24: Performance Security | D24: 履约保证金 | E24: LS | F24: 1
B25: A.1.14 | C25: Advance Payment Guarantee | D25: 预付款保函 | E25: LS | F25: 1
B26: A.1.15 | C26: Parent Company Guarantees | D26: 母公司担保 | E26: LS | F26: 1
B27: A.1.16 | C27: Site Signage | D27: 现场标识 | E27: LS | F27: 1
B28: A.1.17 | C28: Design | D28: 设计
B29: A.1.17.1 | C29: Earthworks Reclamation and Ground Improvement | D29: 土方回填与地基改良 | E29: LS | F29: 1
B30: A.1.17.2 | C30: Quay and other Suspended deck structures | D30: 码头及其他悬挂式甲板结构 | E30: LS | F30: 1
B31: A.1.17.3 | C31: Drainage | D31: 排水工程 | E31: LS | F31: 1
B32: A.1.17.4 | C32: Services and Utilities | D32: 管线及公用设施工程 | E32: LS | F32: 1
B33: A.1.17.5 | C33: Pavements | D33: 路面工程 | E33: LS | F33: 1
B34: A.1.17.6 | C34: Electrical works | D34: 电气工程 | E34: LS | F34: 1
B35: A.1.17.7 | C35: IT and Communications | D35: 信息技术与通信工程 | E35: LS | F35: 1
B36: A.1.17.8 | C36: Gate Complex | D36: 闸口综合体 | E36: LS | F36: 1
B37: A.1.17.9 | C37: Reefer Racks | D37: 冷藏货架 | E37: LS | F37: 1
B38: A.1.17.10 | C38: All other elements | D38: 所有其他要素 | E38: LS | F38: 1
B39: A.1.18 | C39: BIM 3D Modelling | D39: BIM 三维建模 | E39: LS | F39: 1
B40: A.1.19 | C40: Approvals and Permits | D40: 审批与许可证 | E40: LS | F40: 1
B41: A.1.20 | C41: Environmental Compliance Requirements | D41: 环境合规要求
B42: A.1.20.1 | C42: Inputs to Environmental Impact Assessment report (EIA) | D42: 环境影响评估报告（EIA）输入 | E42: LS | F42: 1
B43: A.1.20.2 | C43: Pre-construction plans (specific environmental related plans) | D43: 施工前计划（具体环境相关计划） | E43: LS | F43: 1
B44: A.1.20.3 | C44: Construction phase CEMP | D44: 施工阶段环境管理计划（CEMP） | E44: LS | F44: 1
B45: A.1.20.4 | C45: Protection of drainage systems and watercourses | D45: 排水系统及水体保护 | E45: LS | F45: 1
C46: SUBTOTAL - Fixed (non-time related) Items | D46: 小计 - 固定（非时间相关）要素
B48: A.2 | C48: Time Related Items | D48: 时间相关要素
B49: A.2.1 | C49: Contractor's Supervision | D49: 承包商监督 | E49: Week
B50: A.2.2 | C50: Project Security | D50: 项目安全保障 | E50: Week
B51: A.2.3 | C51: Port Passes | D51: 港口出入证 | E51: Week
B52: A.2.4 | C52: Maintenance of Contractor's Facilities | D52: 承包商设施维护 | E52: Week
B53: A.2.5 | C53: Maintenance of Access Routes | D53: 通行路线维护 | E53: Week
B54: A.2.6 | C54: Maintenance of the Engineer's Facilities | D54: 工程师设施维护 | E54: Week
B55: A.2.7 | C55: Site Welfare | D55: 现场福利设施 | E55: Week
B56: A.2.8 | C56: Safety Equipment & Training | D56: 安全设备与培训 | E56: Week
B57: A.2.9 | C57: Operation of Laboratory | D57: 实验室运行 | E57: Week
B58: A.2.10 | C58: Environmental Monitoring and Reporting | D58: 环境监测与报告 | E58: Week
C59: SUBTOTAL - Time Related Items | D59: 小计 - 时间相关项目
B61: A.3 | C61: As Built Documentation (as per PER 01B) | D61: 竣工文件（依据PER 01B） | E61: LS | F61: 1
C64: Total | D64: 总计 | H64: =SUM(H6:H63) -> 0
B66: Class B | C66: PREPORATORY WORKS (GROUND CLEARANCE, DEMOLITION, SURVEYS, ETC.) | D66: 前期准备工作（场地清理、拆除、勘测等）
C67: The Bill of Quantities is based on the Works shown on the Drawings, however it is the Tenderer's responsibility to verify, validate and adapt the items and quantities in accordance with the Employer's Requirements and its design. Any changes from the Tender BoQ shall be clearly highlighted for clarity. | D67: 工程量清单基于图纸所示工程内容，投标人有责任根据业主要求及其设计，核实、验证并调整项目及数量。投标工程量清单的任何变更应明显标注以确保清晰。
C68: All quantities stated are to be verified by and at the risk of the Contractor. The Employer will accept no liability or claim for extensions to the Time for Completion and/or additional payment as a result of any increases or decreases to the quantities stated, unless instructed through the Contract. | D68: 所有数量均由承包商核实并自行承担风险。除非合同明确指示，业主不承担因数量变化引致工期延长及/或额外付款的任何责任或索赔。 | E68: Quantities left blank are to be inserted by the Tenderer to suit its design.
B70: B.1 | C70: Ground Clearance | D70: 场地清理
A71: =COUNTA(OFFSET(A$1,0,0,ROW()-1,1))+1 -> 1 | B71: B.1.1 | C71: Ground clearance in the container yard area (Block C) | D71: 集装箱堆场区域地面净空（C区块） | E71: m2 | F71: 131000 | G71: 0.30027 | H71: =IFERROR(ROUND(G71*F71,0),0) -> 39335
A72: =COUNTA(OFFSET(A$1,0,0,ROW()-1,1))+1 -> 2 | B72: B.1.2 | C72: Ground clearance in the tidal zones (river side of Block C) | D72: 潮汐区地面净空（C区块河岸侧） | E72: m2 | F72: 31650 | G72: 0.30027 | H72: =IFERROR(ROUND(G72*F72,0),0) -> 9504
A73: =COUNTA(OFFSET(A$1,0,0,ROW()-1,1))+1 -> 3 | B73: B.1.3 | C73: Ground clearance in the drainage channel (between Block B & C) | D73: 排水渠地面净空（B区块与C区块之间） | E73: m2 | F73: 8890 | G73: 0.30027 | H73: =IFERROR(ROUND(G73*F73,0),0) -> 2669
C74: SUBTOTAL - Ground Clearance | D74: 小计 - 地面净空 | G74: 0 | H74: =IFERROR(ROUND(G74*F74,0),0) -> 0
G75: 0 | H75: =IFERROR(ROUND(G75*F75,0),0) -> 0
B76: B.2 | C76: Demolition | D76: 拆除 | G76: 0 | H76: =IFERROR(ROUND(G76*F76,0),0) -> 0
A77: =COUNTA(OFFSET(A$1,0,0,ROW()-1,1))+1 -> 4 | B77: B.2.1 | C77: Demolition of existing boundary walls | D77: 拆除现有边界墙 | E77: m | F77: 4140 | G77: 3.60324 | H77: =IFERROR(ROUND(G77*F77,0),0) -> 14917
A78: =COUNTA(OFFSET(A$1,0,0,ROW()-1,1))+1 -> 5 | B78: B.2.2 | C78: Demolition of existing ferry jetty and associated structures in the drainage channel | D78: 拆除排水渠内现有渡轮码头及相关结构 | E78: LS | F78: 1 | G78: 9608.64 | H78: =IFERROR(ROUND(G78*F78,0),0) -> 9609
A79: =COUNTA(OFFSET(A$1,0,0,ROW()-1,1))+1 -> 6 | B79: B.2.3 | C79: Demolition of existing concrete fence (Block B side of drainage channel) | D79: 拆除现有混凝土围栏（排水渠B区块侧） | E79: m | F79: 290 | G79: 3.60324 | H79: =IFERROR(ROUND(G79*F79,0),0) -> 1045
A80: =COUNTA(OFFSET(A$1,0,0,ROW()-1,1))+1 -> 7 | B80: B.2.4 | C80: Demolition of existing services trench (Block B side of drainage channel) | D80: 拆除现有管线沟槽（排水渠B区块侧） | E80: m | F80: 1 | G80: 4.80432 | H80: =IFERROR(ROUND(G80*F80,0),0) -> 5
A81: =COUNTA(OFFSET(A$1,0,0,ROW()-1,1))+1 -> 8 | B81: B.2.5 | C81: Demolition of existing building in Block C | D81: C区现有建筑物拆除 | E81: No. | F81: 1 | G81: 3603.24 | H81: =IFERROR(ROUND(G81*F81,0),0) -> 3603
A82: =COUNTA(OFFSET(A$1,0,0,ROW()-1,1))+1 -> 9 | B82: B.2.6 | C82: Demolition of existing light towers in Block B | D82: B区现有照明塔拆除 | E82: No. | F82: 6 | G82: 600.54 | H82: =IFERROR(ROUND(G82*F82,0),0) -> 3603
A83: =COUNTA(OFFSET(A$1,0,0,ROW()-1,1))+1 -> 10 | B83: B.2.7 | C83: Demolition of existing seawall and revetment (if applicable to the Contractor's design) | D83: 现有海堤及护岸拆除（如承包商设计所涵盖） | E83: m | F83: 615 | G83: 7.20648 | H83: =IFERROR(ROUND(G83*F83,0),0) -> 4432
B84: B.2.8 | C84: Demolition of existing pavement (minimum extents required for the Contractor's design) | D84: 现有路面拆除（承包商设计所需的最小范围） | E84: m2 | G84: 7.20648 | H84: =IFERROR(ROUND(G84*F84,0),0) -> 0
C85: SUBTOTAL - Demolition | D85: 小计 - 拆除 | G85: 0 | H85: =IFERROR(ROUND(G85*F85,0),0) -> 0
G86: 0 | H86: =IFERROR(ROUND(G86*F86,0),0) -> 0
B87: B.3 | C87: Surveys & Investigations | D87: 测量与调查 | G87: 0 | H87: =IFERROR(ROUND(G87*F87,0),0) -> 0
C88: Contractor to itemise relevant surveys and investigations to suit its proposed methodology | D88: 承包商应根据其拟采用的方法详细列出相关测量与调查项目 | G88: 0 | H88: =IFERROR(ROUND(G88*F88,0),0) -> 0
B89: B.2.1 | C89: Bathymetric survey | D89: 水深测量 | E89: m2 | G89: 0 | H89: =IFERROR(ROUND(G89*F89,0),0) -> 0
B90: B.2.2 | C90: Topgraphic survey | D90: 地形测量 | E90: m2 | G90: 0 | H90: =IFERROR(ROUND(G90*F90,0),0) -> 0
B91: B.2.3 | C91: Contractor to itemise if relevant | D91: 承包商如相关，应予详列 | G91: 0 | H91: =IFERROR(ROUND(G91*F91,0),0) -> 0
C92: SUBTOTAL - Surveys & Investigations | D92: 小计 - 测量与调查 | G92: 0 | H92: =IFERROR(ROUND(G92*F92,0),0) -> 0
G93: 0 | H93: =IFERROR(ROUND(G93*F93,0),0) -> 0
C94: The Tenderer shall separately list and price below any other items that it considers applicable. | D94: 投标人应另行列出并报价其认为适用的其他项目。 | G94: 0 | H94: =IFERROR(ROUND(G94*F94,0),0) -> 0
G95: 0 | H95: =IFERROR(ROUND(G95*F95,0),0) -> 0
C96: Total | D96: 总计 | G96: 0 | H96: =SUM(H67:H95) -> 88722
G97: 0 | H97: =IFERROR(ROUND(G97*F97,0),0) -> 0
B98: Class C | C98: DREDGING (PER 003) | D98: 疏浚（依据003条款） | G98: 0 | H98: =IFERROR(ROUND(G98*F98,0),0) -> 0
C99: The Bill of Quantities is based on the Works shown on the Drawings, however it is the Tenderer's responsibility to verify, validate and adapt the items and quantities in accordance with the Employer's Requirements and its design. Any changes from the Tender BoQ shall be clearly highlighted for clarity. | D99: 工程量清单基于图纸所示工程内容，投标人有责任根据业主要求及其设计，核实、验证并调整项目及数量。投标工程量清单的任何变更应明显标注以确保清晰。 | G99: 0 | H99: =IFERROR(ROUND(G99*F99,0),0) -> 0
C100: All quantities stated are to be verified by and at the risk of the Contractor. The Employer will accept no liability or claim for extensions to the Time for Completion and/or additional payment as a result of any increases or decreases to the quantities stated, unless instructed through the Contract. | D100: 所有数量均由承包商核实并自行承担风险。除非合同明确指示，业主不承担因数量变化引致工期延长及/或额外付款的任何责任或索赔。 | E100: Quantities left blank are to be inserted by the Tenderer to suit its design. | G100: 0 | H100: =IFERROR(ROUND(G100*F100,0),0) -> 0
G101: 0 | H101: =IFERROR(ROUND(G101*F101,0),0) -> 0
B102: C.1 | C102: General | D102: 一般条款 | G102: 0 | H102: =IFERROR(ROUND(G102*F102,0),0) -> 0
B103: C.1.1 | C103: Mobilisation of marine dredging equipment | D103: 海洋疏浚设备的动员部署 | E103: LS | F103: 0 | G103: 0 | H103: =IFERROR(ROUND(G103*F103,0),0) -> 0
B104: C.1.2 | C104: Demobilisation of marine dredging equipment | D104: 海洋疏浚设备的撤离 | E104: LS | F104: 0 | G104: 0 | H104: =IFERROR(ROUND(G104*F104,0),0) -> 0
G105: 0 | H105: =IFERROR(ROUND(G105*F105,0),0) -> 0
B106: C.2 | C106: Dredging of loose to medium dense material and disposal at approved location (including desposal at an approved location) | D106: 疏浚松散至中密实材料并运至批准地点处置（含在经批准地点的处置） | G106: 0 | H106: =IFERROR(ROUND(G106*F106,0),0) -> 0
B107: C.2.1 | C107: Berthing pocket | D107: 泊位凹槽 | E107: m3 | F107: 0 | G107: 0 | H107: =IFERROR(ROUND(G107*F107,0),0) -> 0
...
